README.md
setup.py
niu_scooter/__init__.py
niu_scooter/niu.py
niu_scooter.egg-info/PKG-INFO
niu_scooter.egg-info/SOURCES.txt
niu_scooter.egg-info/dependency_links.txt
niu_scooter.egg-info/top_level.txt