Metadata-Version: 2.1
Name: niu-scooter
Version: 0.0.5
Summary: niu scoote api
Home-page: https://github.com/
Author: yangbo1979
Author-email: gyangbo@gmail.com
License: UNKNOWN
Platform: UNKNOWN
Classifier: Programming Language :: Python :: 3
Classifier: License :: OSI Approved :: MIT License
Classifier: Operating System :: OS Independent
